pandas_lint/__init__.py
pandas_lint/analyzer.py
pandas_lint/cli.py
pandas_lint/fixer.py
pandas_lint/notebook.py
pandas_lint/rules.py
pandas_linter-0.1.0.dist-info/licenses/LICENSE
pandas_linter-0.1.0.dist-info/METADATA
pandas_linter-0.1.0.dist-info/WHEEL
pandas_linter-0.1.0.dist-info/entry_points.txt
pandas_linter-0.1.0.dist-info/top_level.txt
pandas_linter-0.1.0.dist-info/RECORD
