Metadata-Version: 2.4
Name: pandas-linter
Version: 0.1.0
Summary: Static linter to optimize Pandas/Numpy code
Author-email: Jean Estevez <ctarriba9@gmail.com>
Maintainer-email: Jean Estevez <ctarriba9@gmail.com>
License: MIT License
Project-URL: Homepage, https://github.com/Jean-EstevezT/pandas_lint
Project-URL: Repository, https://github.com/Jean-EstevezT/pandas_lint
Project-URL: Issues, https://github.com/Jean-EstevezT/pandas_lint/issues
Keywords: pandas,lint,static analysis,optimization,data science
Classifier: Development Status :: 3 - Alpha
Classifier: Intended Audience :: Developers
Classifier: Intended Audience :: Science/Research
Classifier: License :: OSI Approved :: MIT License
Classifier: Programming Language :: Python :: 3
Classifier: Programming Language :: Python :: 3.8
Classifier: Programming Language :: Python :: 3.9
Classifier: Programming Language :: Python :: 3.10
Classifier: Programming Language :: Python :: 3.11
Classifier: Topic :: Software Development :: Quality Assurance
Classifier: Topic :: Scientific/Engineering :: Information Analysis
Requires-Python: >=3.8
License-File: LICENSE
Requires-Dist: click
Requires-Dist: rich
Requires-Dist: toml
Requires-Dist: libcst
Provides-Extra: dev
Requires-Dist: pytest; extra == "dev"
Requires-Dist: pytest-cov; extra == "dev"
Requires-Dist: black; extra == "dev"
Requires-Dist: isort; extra == "dev"
Requires-Dist: flake8; extra == "dev"
Requires-Dist: build; extra == "dev"
Requires-Dist: twine; extra == "dev"
Dynamic: license-file
